odoo/addons/partner_brand/README.rst
odoo/addons/partner_brand/__init__.py
odoo/addons/partner_brand/__manifest__.py
odoo/addons/partner_brand/data/res_brand_demo.xml
odoo/addons/partner_brand/data/res_partner_demo.xml
odoo/addons/partner_brand/i18n/es.po
odoo/addons/partner_brand/i18n/fr.po
odoo/addons/partner_brand/i18n/it.po
odoo/addons/partner_brand/i18n/nl.po
odoo/addons/partner_brand/i18n/partner_brand.pot
odoo/addons/partner_brand/models/__init__.py
odoo/addons/partner_brand/models/partner.py
odoo/addons/partner_brand/readme/CONTRIBUTORS.md
odoo/addons/partner_brand/readme/DESCRIPTION.md
odoo/addons/partner_brand/static/description/brand.png
odoo/addons/partner_brand/static/description/brand_form.png
odoo/addons/partner_brand/static/description/brand_kanban.png
odoo/addons/partner_brand/static/description/brand_tree.png
odoo/addons/partner_brand/static/description/carrouf.png
odoo/addons/partner_brand/static/description/icon.png
odoo/addons/partner_brand/static/description/index.html
odoo/addons/partner_brand/static/description/lyon.jpg
odoo/addons/partner_brand/static/description/walmart.jpg
odoo/addons/partner_brand/static/description/walmart.png
odoo/addons/partner_brand/tests/__init__.py
odoo/addons/partner_brand/tests/test_partner_brand.py
odoo/addons/partner_brand/views/partner.xml
odoo_addon_partner_brand-18.0.1.0.2.dist-info/METADATA
odoo_addon_partner_brand-18.0.1.0.2.dist-info/WHEEL
odoo_addon_partner_brand-18.0.1.0.2.dist-info/top_level.txt
odoo_addon_partner_brand-18.0.1.0.2.dist-info/RECORD
