Metadata-Version: 2.1
Name: odoo-addon-partner_brand
Version: 18.0.1.0.2
Requires-Python: >=3.10
Requires-Dist: odoo-addon-brand==18.0.*
Requires-Dist: odoo==18.0.*
Summary: Define registered mark in partners according to brand settings
Home-page: https://github.com/OCA/brand
License: AGPL-3
Author: Odoo Community Association (OCA), Akretion
Author-email: support@odoo-community.org
Classifier: Programming Language :: Python
Classifier: Framework :: Odoo
Classifier: Framework :: Odoo :: 18.0
Classifier: License :: OSI Approved :: GNU Affero General Public License v3
Classifier: Development Status :: 3 - Alpha
